codegen.py
bb/COW.py
bb/__init__.py
bb/acl.py
bb/build.py
bb/cache.py
bb/cache_extra.py
bb/checksum.py
bb/codeparser.py
bb/command.py
bb/cooker.py
bb/cookerdata.py
bb/daemonize.py
bb/data.py
bb/data_smart.py
bb/event.py
bb/filter.py
bb/main.py
bb/methodpool.py
bb/monitordisk.py
bb/msg.py
bb/namedtuple_with_abc.py
bb/process.py
bb/progress.py
bb/providers.py
bb/remotedata.py
bb/runqueue.py
bb/siggen.py
bb/taskdata.py
bb/tinfoil.py
bb/utils.py
bb/xattr.py
bb/asyncrpc/__init__.py
bb/asyncrpc/client.py
bb/asyncrpc/connection.py
bb/asyncrpc/exceptions.py
bb/asyncrpc/serv.py
bb/fetch2/__init__.py
bb/fetch2/az.py
bb/fetch2/bzr.py
bb/fetch2/clearcase.py
bb/fetch2/crate.py
bb/fetch2/cvs.py
bb/fetch2/gcp.py
bb/fetch2/git.py
bb/fetch2/gitannex.py
bb/fetch2/gitsm.py
bb/fetch2/gomod.py
bb/fetch2/hg.py
bb/fetch2/local.py
bb/fetch2/npm.py
bb/fetch2/npmsw.py
bb/fetch2/osc.py
bb/fetch2/perforce.py
bb/fetch2/repo.py
bb/fetch2/s3.py
bb/fetch2/sftp.py
bb/fetch2/ssh.py
bb/fetch2/svn.py
bb/fetch2/wget.py
bb/parse/__init__.py
bb/parse/ast.py
bb/parse/parse_py/BBHandler.py
bb/parse/parse_py/ConfHandler.py
bb/parse/parse_py/__init__.py
bb/pysh/__init__.py
bb/pysh/pyshlex.py
bb/pysh/pyshyacc.py
bb/pysh/sherrors.py
bb/server/__init__.py
bb/server/process.py
bb/server/xmlrpcclient.py
bb/server/xmlrpcserver.py
bb/tests/__init__.py
bb/tests/codeparser.py
bb/tests/color.py
bb/tests/compression.py
bb/tests/cooker.py
bb/tests/cow.py
bb/tests/data.py
bb/tests/event.py
bb/tests/fetch.py
bb/tests/filter.py
bb/tests/parse.py
bb/tests/runqueue.py
bb/tests/setup.py
bb/tests/siggen.py
bb/tests/utils.py
bb/ui/__init__.py
bb/ui/buildinfohelper.py
bb/ui/eventreplay.py
bb/ui/knotty.py
bb/ui/ncurses.py
bb/ui/taskexp.py
bb/ui/taskexp_ncurses.py
bb/ui/teamcity.py
bb/ui/toasterui.py
bb/ui/uievent.py
bb/ui/uihelper.py
bitbake_setup/__init__.py
bitbake_setup/__main__.py
bs4/__init__.py
bs4/css.py
bs4/dammit.py
bs4/diagnose.py
bs4/element.py
bs4/formatter.py
bs4/builder/__init__.py
bs4/builder/_html5lib.py
bitbake_setup-2.16.0a1.dist-info/METADATA
bitbake_setup-2.16.0a1.dist-info/WHEEL
bitbake_setup-2.16.0a1.dist-info/entry_points.txt
bitbake_setup-2.16.0a1.dist-info/top_level.txt
bitbake_setup-2.16.0a1.dist-info/RECORD
