Metadata-Version: 2.4
Name: bitbake-setup
Version: 2.16.0a1
Summary: bitbake-setup
Home-page: https://github.com/openembedded/bitbake.git
Author: OpenEmbedded BitBake Developers
Author-email: bitbake-devel@lists.openembedded.org
License: "MIT"
Classifier: Programming Language :: Python :: 3
Classifier: Operating System :: OS Independent
Requires-Python: >=3.6
